paradex_cli/__init__.py
paradex_cli/main.py
paradex_cli-0.1.4.dist-info/METADATA
paradex_cli-0.1.4.dist-info/WHEEL
paradex_cli-0.1.4.dist-info/entry_points.txt
paradex_cli-0.1.4.dist-info/licenses/LICENSE
paradex_cli-0.1.4.dist-info/RECORD
