Metadata-Version: 2.4
Name: paradex-cli
Version: 0.1.4
Summary: CLI for interacting with Paradex API and Paraclear smart contracts
License: MIT
License-File: LICENSE
Author: Paradex Team
Author-email: support@paradex.trade
Requires-Python: >=3.10,<3.13
Classifier: License :: OSI Approved :: MIT License
Classifier: Programming Language :: Python :: 3
Classifier: Programming Language :: Python :: 3.10
Classifier: Programming Language :: Python :: 3.11
Classifier: Programming Language :: Python :: 3.12
Requires-Dist: paradex_py (>=0.5.1,<0.6.0)
Requires-Dist: rich (>=14.0.0,<15.0.0)
Requires-Dist: typer[all] (>=0.15.2,<0.16.0)
